pysb/units/__init__.py
pysb/units/core.py
pysb/units/unitdefs.py
pysb/units/examples/__init__.py
pysb/units/examples/bngwiki_simple.py
pysb/units/examples/jnk3_no_ask1.py
pysb_units-0.4.1.dist-info/licenses/LICENSE
pysb_units-0.4.1.dist-info/METADATA
pysb_units-0.4.1.dist-info/WHEEL
pysb_units-0.4.1.dist-info/top_level.txt
pysb_units-0.4.1.dist-info/RECORD
