Metadata-Version: 2.4
Name: pysb-units
Version: 0.4.1
Summary: PySB add-on providing utilities to add units to models.
Author-email: "Blake A. Wilson" <blakeaw1102@gmail.com>
Project-URL: Repository, https://github.com/Borealis-BioModeling/pysb-units
Project-URL: Issues, https://github.com/Borealis-BioModeling/pysb-units/issues
Project-URL: Changelog, https://github.com/Borealis-BioModeling/pysb-units/blob/master/CHANGELOG.md
Keywords: pysb,biomodels,reaction models,systems biology
Classifier: Development Status :: 3 - Alpha
Classifier: Intended Audience :: Science/Research
Classifier: Topic :: Software Development :: Libraries :: Python Modules
Classifier: Topic :: Scientific/Engineering
Classifier: Topic :: Scientific/Engineering :: Chemistry
Classifier: License :: OSI Approved :: BSD License
Classifier: Programming Language :: Python
Classifier: Programming Language :: Python :: 3
Requires-Python: >=3.8
License-File: LICENSE
Requires-Dist: pysb>=1.15.0
Requires-Dist: sympy>=1.11.1
Requires-Dist: astropy>=5.3.4
Dynamic: license-file
